Metadata-Version: 2.1
Name: TACalculator-v1
Version: 0.1
Summary: Simple calculator, performing basic functions
Author: Tauras Aleksandravicius
Author-email: tauras.al@gmail.com
Classifier: Programming Language :: Python :: 3
Classifier: License :: OSI Approved :: MIT License
Classifier: Operating System :: OS Independent
License-File: LICENSE
